easyCodes/__init__.py
easyCodes-0.0.2.dist-info/LICENSE.txt
easyCodes-0.0.2.dist-info/METADATA
easyCodes-0.0.2.dist-info/WHEEL
easyCodes-0.0.2.dist-info/top_level.txt
easyCodes-0.0.2.dist-info/RECORD
