Metadata-Version: 2.1
Name: easyCodes
Version: 0.0.2
Summary: Get general utility algorithms in output to use
Home-page: UNKNOWN
Author: Amit Kumar
Author-email: amit.kumar221099@gmail.com
License: MIT
Platform: UNKNOWN
Classifier: Development Status :: 5 - Production/Stable
Classifier: Intended Audience :: Education
Classifier: Operating System :: Microsoft :: Windows :: Windows 10
Classifier: License :: OSI Approved :: MIT License
Classifier: Programming Language :: Python :: 3
